mpris_scrobbler/__init__.py
mpris_scrobbler/__main__.py
mpris_scrobbler/scrobble.py
mpris_scrobbler/services/wiltfm.py
mpris_scrobbler-0.0.3.data/scripts/__init__.py
mpris_scrobbler-0.0.3.data/scripts/__main__.py
mpris_scrobbler-0.0.3.data/scripts/mpris_scrobbler
mpris_scrobbler-0.0.3.dist-info/DESCRIPTION.rst
mpris_scrobbler-0.0.3.dist-info/METADATA
mpris_scrobbler-0.0.3.dist-info/RECORD
mpris_scrobbler-0.0.3.dist-info/WHEEL
mpris_scrobbler-0.0.3.dist-info/metadata.json
mpris_scrobbler-0.0.3.dist-info/top_level.txt
