Metadata-Version: 2.0
Name: mpris-scrobbler
Version: 0.0.3
Summary: Scrobbler that can use any MPRIS-enabled media players.
Home-page: https://sina.mashek.xyz/projects/mpris_scrobbler
Author: Sina Mashek
Author-email: sina@mashek.xyz
License: MIT
Platform: any
Classifier: Development Status :: 3 - Alpha
Classifier: Environment :: Console
Classifier: License :: OSI Approved :: MIT License
Classifier: Programming Language :: Python :: 3
Classifier: Programming Language :: Python :: 3.2
Classifier: Programming Language :: Python :: 3.3
Classifier: Programming Language :: Python :: 3.4
Classifier: Programming Language :: Python :: 3.5
Classifier: Programming Language :: Python :: 3.6
